{
  "metadata" : {
    "realm" : null,
    "amsterVersion" : "7.0.0-SNAPSHOT",
    "entityType" : "OAuth2Provider",
    "entityId" : "1.0",
    "serviceVersion" : null,
    "uid" : "ou=1.0,ou=OAuth2Provider,ou=services,ou=am-config",
    "sunServiceID" : null,
    "objectClass" : [ "top", "sunService" ],
    "pathParams" : { },
    "ou" : [ ]
  },
  "data" : {
    "defaults" : {
      "coreOAuth2Config" : {
        "refreshTokenLifetime" : 604800,
        "accessTokenLifetime" : 3600,
        "usePolicyEngineForScope" : false,
        "codeLifetime" : 120,
        "issueRefreshTokenOnRefreshedToken" : true,
        "issueRefreshToken" : true,
        "accessTokenModificationScript" : "d22f9a0c-426a-4466-b95e-d0f125b0d5fa",
        "statelessTokensEnabled" : false
      },
      "advancedOAuth2Config" : {
        "customLoginUrlTemplate" : null,
        "supportedScopes" : [ ],
        "codeVerifierEnforced" : "false",
        "tokenSigningAlgorithm" : "HS256",
        "authenticationAttributes" : [ "uid" ],
        "passwordGrantAuthService" : null,
        "defaultScopes" : [ ],
        "tlsClientCertificateTrustedHeader" : null,
        "scopeImplementationClass" : "org.forgerock.openam.oauth2.OpenAMScopeValidator",
        "modifiedTimestampAttribute" : null,
        "responseTypeClasses" : [ "code|org.forgerock.oauth2.core.AuthorizationCodeResponseTypeHandler", "device_code|org.forgerock.oauth2.core.TokenResponseTypeHandler", "token|org.forgerock.oauth2.core.TokenResponseTypeHandler" ],
        "tlsCertificateBoundAccessTokensEnabled" : true,
        "hashSalt" : null,
        "moduleMessageEnabledInPasswordGrant" : false,
        "tokenCompressionEnabled" : null,
        "tokenEncryptionEnabled" : false,
        "grantTypes" : [ "implicit", "refresh_token", "urn:ietf:params:oauth:grant-type:saml2-bearer", "password", "client_credentials", "urn:ietf:params:oauth:grant-type:device_code", "authorization_code", "urn:openid:params:grant-type:ciba", "urn:ietf:params:oauth:grant-type:uma-ticket", "urn:ietf:params:oauth:grant-type:jwt-bearer" ],
        "createdTimestampAttribute" : null,
        "displayNameAttribute" : "cn",
        "supportedSubjectTypes" : [ "public" ]
      },
      "coreOIDCConfig" : {
        "supportedIDTokenEncryptionMethods" : [ "A256GCM", "A192GCM", "A128GCM", "A128CBC-HS256", "A192CBC-HS384", "A256CBC-HS512" ],
        "jwtTokenLifetime" : 3600,
        "supportedClaims" : [ ],
        "supportedIDTokenEncryptionAlgorithms" : [ "RSA-OAEP", "RSA-OAEP-256", "A128KW", "RSA1_5", "A256KW", "dir", "A192KW" ],
        "supportedIDTokenSigningAlgorithms" : [ "PS384", "RS384", "ES384", "HS256", "HS512", "ES256", "RS256", "HS384", "ES512", "PS256", "PS512", "RS512" ],
        "oidcClaimsScript" : "36863ffb-40ec-48b9-94b1-9a99f71cc3b5"
      },
      "MapValueValidator" : "com.sun.identity.common.configuration.MapValueValidator",
      "clientDynamicRegistrationConfig" : {
        "dynamicClientRegistrationSoftwareStatementRequired" : false,
        "dynamicClientRegistrationScope" : "dynamic_client_registration",
        "requiredSoftwareStatementAttestedAttributes" : [ "redirect_uris" ],
        "generateRegistrationAccessTokens" : true,
        "allowDynamicRegistration" : false
      },
      "advancedOIDCConfig" : {
        "storeOpsTokens" : true,
        "defaultACR" : [ ],
        "supportedRequestParameterEncryptionEnc" : [ "A256GCM", "A192GCM", "A128GCM", "A128CBC-HS256", "A192CBC-HS384", "A256CBC-HS512" ],
        "claimsParameterSupported" : false,
        "amrMappings" : { },
        "supportedUserInfoEncryptionEnc" : [ "A256GCM", "A192GCM", "A128GCM", "A128CBC-HS256", "A192CBC-HS384", "A256CBC-HS512" ],
        "alwaysAddClaimsToToken" : false,
        "supportedUserInfoSigningAlgorithms" : [ "ES384", "HS256", "HS512", "ES256", "RS256", "HS384", "ES512" ],
        "supportedRequestParameterEncryptionAlgorithms" : [ "RSA-OAEP", "RSA-OAEP-256", "A128KW", "RSA1_5", "A256KW", "dir", "A192KW" ],
        "supportedTokenIntrospectionResponseEncryptionEnc" : [ "A256GCM", "A192GCM", "A128GCM", "A128CBC-HS256", "A192CBC-HS384", "A256CBC-HS512" ],
        "supportedTokenIntrospectionResponseSigningAlgorithms" : [ "PS384", "RS384", "EdDSA", "ES384", "HS256", "HS512", "ES256", "RS256", "HS384", "ES512", "PS256", "PS512", "RS512" ],
        "authorisedOpenIdConnectSSOClients" : [ ],
        "idTokenInfoClientAuthenticationEnabled" : true,
        "supportedRequestParameterSigningAlgorithms" : [ "PS384", "RS384", "ES384", "HS256", "HS512", "ES256", "RS256", "HS384", "ES512", "PS256", "PS512", "RS512" ],
        "supportedUserInfoEncryptionAlgorithms" : [ "RSA-OAEP", "RSA-OAEP-256", "A128KW", "A256KW", "RSA1_5", "dir", "A192KW" ],
        "supportedTokenEndpointAuthenticationSigningAlgorithms" : [ "PS384", "RS384", "ES384", "HS256", "HS512", "ES256", "RS256", "HS384", "ES512", "PS256", "PS512", "RS512" ],
        "supportedTokenIntrospectionResponseEncryptionAlgorithms" : [ "RSA-OAEP", "RSA-OAEP-256", "A128KW", "A256KW", "RSA1_5", "dir", "A192KW" ],
        "loaMapping" : { },
        "jkwsURI" : null
      },
      "cibaConfig" : {
        "supportedCibaSigningAlgorithms" : [ "ES256", "PS256" ],
        "cibaAuthReqIdLifetime" : 600,
        "cibaMinimumPollingInterval" : 2
      },
      "consent" : {
        "enableRemoteConsent" : false,
        "supportedRcsRequestSigningAlgorithms" : [ "PS384", "RS384", "ES384", "HS256", "HS512", "ES256", "RS256", "HS384", "ES512", "PS256", "PS512", "RS512" ],
        "supportedRcsResponseSigningAlgorithms" : [ "PS384", "RS384", "ES384", "HS256", "HS512", "ES256", "RS256", "HS384", "ES512", "PS256", "PS512", "RS512" ],
        "clientsCanSkipConsent" : false,
        "supportedRcsRequestEncryptionAlgorithms" : [ "RSA-OAEP", "RSA-OAEP-256", "A128KW", "RSA1_5", "A256KW", "dir", "A192KW" ],
        "supportedRcsResponseEncryptionMethods" : [ "A256GCM", "A192GCM", "A128GCM", "A128CBC-HS256", "A192CBC-HS384", "A256CBC-HS512" ],
        "supportedRcsRequestEncryptionMethods" : [ "A256GCM", "A192GCM", "A128GCM", "A128CBC-HS256", "A192CBC-HS384", "A256CBC-HS512" ],
        "remoteConsentServiceId" : null,
        "savedConsentAttribute" : "",
        "supportedRcsResponseEncryptionAlgorithms" : [ "RSA-OAEP", "RSA-OAEP-256", "A128KW", "RSA1_5", "A256KW", "dir", "A192KW" ]
      },
      "deviceCodeConfig" : {
        "devicePollInterval" : 5,
        "completionUrl" : null,
        "deviceCodeLifetime" : 300,
        "verificationUrl" : null
      },
      "ListValueValidator" : "com.sun.identity.common.configuration.ListValueValidator"
    },
    "sunServiceSchema" : "<?xml version=\"1.0\" encoding=\"UTF-8\"?>\n\n<ServicesConfiguration><Service name=\"OAuth2Provider\" version=\"1.0\"><Schema i18nFileName=\"OAuth2Provider\"  i18nKey=\"forgerock-oauth2-provider-description\"  resourceName=\"oauth-oidc\"  revisionNumber=\"1\"  serviceHierarchy=\"/DSAMEConfig/ForgerockOAuth2ProviderService\"  serviceVersion=\"b4fa55f7-7016-4cc4-8b75-39b6df2e4a4c\" >\n            <Global hideConfigUI=\"no\"  validate=\"yes\" >\n                <AttributeSchema cosQualifier=\"default\"  hideConfigUI=\"no\"  isSearchable=\"no\"  listOrder=\"natural\"  name=\"blacklistingEnabled\"  syntax=\"boolean\"  type=\"single\" >\n                    <BooleanValues>\n                        <BooleanTrueValue i18nKey=\"i18nTrue\" >true</BooleanTrueValue>\n                        <BooleanFalseValue i18nKey=\"i18nFalse\" >false</BooleanFalseValue>\n                    </BooleanValues>\n                    <DefaultValues>\n                        <Value>true</Value>\n                    </DefaultValues>\n                </AttributeSchema>\n                <AttributeSchema cosQualifier=\"default\"  hideConfigUI=\"no\"  i18nKey=\"a134\"  isSearchable=\"no\"  listOrder=\"natural\"  name=\"blacklistCacheSize\"  order=\"0\"  rangeEnd=\"2147483647\"  rangeStart=\"0\"  syntax=\"number_range\"  type=\"single\" >\n                    <DefaultValues>\n                        <Value>10000</Value>\n                    </DefaultValues>\n                </AttributeSchema>\n                <AttributeSchema cosQualifier=\"default\"  hideConfigUI=\"no\"  i18nKey=\"a135\"  isSearchable=\"no\"  listOrder=\"natural\"  name=\"blacklistPollInterval\"  order=\"1\"  rangeEnd=\"2147483647\"  rangeStart=\"0\"  syntax=\"number_range\"  type=\"single\" >\n                    <DefaultValues>\n                        <Value>60</Value>\n                    </DefaultValues>\n                </AttributeSchema>\n                <AttributeSchema cosQualifier=\"default\"  hideConfigUI=\"no\"  i18nKey=\"a136\"  isSearchable=\"no\"  listOrder=\"natural\"  name=\"blacklistPurgeDelay\"  order=\"2\"  rangeEnd=\"2147483647\"  rangeStart=\"0\"  syntax=\"number_range\"  type=\"single\" >\n                    <DefaultValues>\n                        <Value>1</Value>\n                    </DefaultValues>\n                </AttributeSchema>\n                <AttributeSchema cosQualifier=\"default\"  hideConfigUI=\"no\"  i18nKey=\"statelessGrantTokenUpgradeCompatibilityMode\"  isSearchable=\"no\"  listOrder=\"natural\"  name=\"statelessGrantTokenUpgradeCompatibilityMode\"  order=\"5\"  syntax=\"boolean\"  type=\"single\" >\n                    <BooleanValues>\n                        <BooleanTrueValue i18nKey=\"i18nTrue\" >true</BooleanTrueValue>\n                        <BooleanFalseValue i18nKey=\"i18nFalse\" >false</BooleanFalseValue>\n                    </BooleanValues>\n                    <DefaultValues>\n                        <Value>false</Value>\n                    </DefaultValues>\n                </AttributeSchema>\n                <AttributeSchema cosQualifier=\"default\"  hideConfigUI=\"no\"  i18nKey=\"storageScheme\"  isSearchable=\"no\"  listOrder=\"natural\"  name=\"storageScheme\"  order=\"6\"  syntax=\"string\"  type=\"single_choice\" >\n                    <ChoiceValues>\n                        <ChoiceValue i18nKey=\"choice1OneToOneStorageScheme\" >CTS_ONE_TO_ONE_MODEL</ChoiceValue>\n                        <ChoiceValue i18nKey=\"choice2GrantSetModelStorageScheme\" >CTS_GRANT_SET_MODEL</ChoiceValue>\n                    </ChoiceValues>\n                    <DefaultValues>\n                        <Value>CTS_ONE_TO_ONE_MODEL</Value>\n                    </DefaultValues>\n                </AttributeSchema>\n                <AttributeSchema cosQualifier=\"default\"  hideConfigUI=\"no\"  i18nKey=\"jwtTokenLifetimeValidationEnabled\"  isSearchable=\"no\"  listOrder=\"natural\"  name=\"jwtTokenLifetimeValidationEnabled\"  order=\"7\"  syntax=\"boolean\"  type=\"single\" >\n                    <DefaultValues>\n                        <Value>true</Value>\n                    </DefaultValues>\n                </AttributeSchema>\n                <AttributeSchema cosQualifier=\"default\"  hideConfigUI=\"no\"  i18nKey=\"jwtTokenUnreasonableLifetime\"  isSearchable=\"no\"  listOrder=\"natural\"  name=\"jwtTokenUnreasonableLifetime\"  order=\"8\"  syntax=\"number\"  type=\"single\" >\n                    <DefaultValues>\n                        <Value>86400</Value>\n                    </DefaultValues>\n                </AttributeSchema>\n            </Global>\n            <Organization hideConfigUI=\"no\" >\n                <AttributeSchema cosQualifier=\"default\"  hideConfigUI=\"no\"  i18nKey=\"a099\"  isSearchable=\"no\"  listOrder=\"natural\"  name=\"statelessTokensEnabled\"  order=\"3\"  syntax=\"boolean\"  type=\"single\" >\n                    <BooleanValues>\n                        <BooleanTrueValue i18nKey=\"i18nTrue\" >true</BooleanTrueValue>\n                        <BooleanFalseValue i18nKey=\"i18nFalse\" >false</BooleanFalseValue>\n                    </BooleanValues>\n                    <DefaultValues>\n                        <Value>false</Value>\n                    </DefaultValues>\n                </AttributeSchema>\n                <AttributeSchema cosQualifier=\"default\"  hideConfigUI=\"no\"  i18nKey=\"a100\"  isSearchable=\"no\"  listOrder=\"natural\"  name=\"forgerock-oauth2-provider-authorization-code-lifetime\"  order=\"10\"  rangeEnd=\"2147483647\"  rangeStart=\"0\"  resourceName=\"codeLifetime\"  syntax=\"number_range\"  type=\"single\"  validator=\"RequiredValueValidator\" >\n                    <DefaultValues>\n                        <Value>120</Value>\n                    </DefaultValues>\n                </AttributeSchema>\n\n                <AttributeSchema cosQualifier=\"default\"  hideConfigUI=\"no\"  i18nKey=\"a101\"  isSearchable=\"no\"  listOrder=\"natural\"  name=\"forgerock-oauth2-provider-refresh-token-lifetime\"  order=\"20\"  rangeEnd=\"2147483647\"  rangeStart=\"-1\"  resourceName=\"refreshTokenLifetime\"  syntax=\"number_range\"  type=\"single\"  validator=\"RequiredValueValidator\" >\n                    <DefaultValues>\n                        <Value>604800</Value>\n                    </DefaultValues>\n                </AttributeSchema>\n\n                <AttributeSchema cosQualifier=\"default\"  hideConfigUI=\"no\"  i18nKey=\"a102\"  isSearchable=\"no\"  listOrder=\"natural\"  name=\"forgerock-oauth2-provider-access-token-lifetime\"  order=\"30\"  rangeEnd=\"2147483647\"  rangeStart=\"0\"  resourceName=\"accessTokenLifetime\"  syntax=\"number_range\"  type=\"single\"  validator=\"RequiredValueValidator\" >\n                    <DefaultValues>\n                        <Value>3600</Value>\n                    </DefaultValues>\n                </AttributeSchema>\n\n                <AttributeSchema cosQualifier=\"default\"  hideConfigUI=\"no\"  i18nKey=\"a103\"  isSearchable=\"no\"  listOrder=\"natural\"  name=\"forgerock-oauth2-provider-issue-refresh-token\"  order=\"40\"  resourceName=\"issueRefreshToken\"  syntax=\"boolean\"  type=\"single\" >\n                    <BooleanValues>\n                        <BooleanTrueValue i18nKey=\"i18nTrue\" >true</BooleanTrueValue>\n                        <BooleanFalseValue i18nKey=\"i18nFalse\" >false</BooleanFalseValue>\n                    </BooleanValues>\n                    <DefaultValues>\n                        <Value>true</Value>\n                    </DefaultValues>\n                </AttributeSchema>\n\n                <AttributeSchema cosQualifier=\"default\"  hideConfigUI=\"no\"  i18nKey=\"a103a\"  isSearchable=\"no\"  listOrder=\"natural\"  name=\"forgerock-oauth2-provider-issue-refresh-token-on-refreshing-token\"  order=\"50\"  resourceName=\"issueRefreshTokenOnRefreshedToken\"  syntax=\"boolean\"  type=\"single\" >\n                    <BooleanValues>\n                        <BooleanTrueValue i18nKey=\"i18nTrue\" >true</BooleanTrueValue>\n                        <BooleanFalseValue i18nKey=\"i18nFalse\" >false</BooleanFalseValue>\n                    </BooleanValues>\n                    <DefaultValues>\n                        <Value>true</Value>\n                    </DefaultValues>\n                </AttributeSchema>\n\n                <AttributeSchema cosQualifier=\"default\"  hideConfigUI=\"no\"  i18nKey=\"a103b\"  isSearchable=\"no\"  listOrder=\"natural\"  name=\"customLoginUrlTemplate\"  order=\"60\"  syntax=\"string\"  type=\"single\" >\n                    <IsOptional></IsOptional>\n                </AttributeSchema>\n\n                <AttributeSchema cosQualifier=\"default\"  hideConfigUI=\"no\"  i18nKey=\"a104\"  isSearchable=\"no\"  listOrder=\"natural\"  name=\"forgerock-oauth2-provider-scope-implementation-class\"  order=\"70\"  resourceName=\"scopeImplementationClass\"  syntax=\"string\"  type=\"single\"  validator=\"RequiredValueValidator\" >\n                    <DefaultValues>\n                        <Value>org.forgerock.openam.oauth2.OpenAMScopeValidator</Value>\n                    </DefaultValues>\n                </AttributeSchema>\n\n                <AttributeSchema cosQualifier=\"default\"  hideConfigUI=\"no\"  i18nKey=\"accessTokenModificationScript\"  isSearchable=\"no\"  listOrder=\"natural\"  name=\"oauth2-provider-access-token-modification-script\"  order=\"75\"  propertiesViewBeanURL=\"../ui-admin/%23realms/{0}/scripts/edit/{1}\"  resourceName=\"accessTokenModificationScript\"  syntax=\"string\"  type=\"single_choice\"  uitype=\"scriptSelect\" >\n                    <ChoiceValues>\n                        <ChoiceValuesClassName className=\"org.forgerock.openam.scripting.service.ScriptChoiceValues\" >\n                            <AttributeValuePair>\n                                <Attribute name=\"ContextId\" ></Attribute>\n                                <Value>OAUTH2_ACCESS_TOKEN_MODIFICATION</Value>\n                            </AttributeValuePair>\n                        </ChoiceValuesClassName>\n                    </ChoiceValues>\n                    <DefaultValues>\n                        <Value>d22f9a0c-426a-4466-b95e-d0f125b0d5fa</Value>\n                    </DefaultValues>\n                </AttributeSchema>\n\n                <AttributeSchema cosQualifier=\"default\"  hideConfigUI=\"no\"  i18nKey=\"a104aa\"  isSearchable=\"no\"  listOrder=\"natural\"  name=\"forgerock-oauth2-provider-oidc-claims-extension-script\"  order=\"80\"  propertiesViewBeanURL=\"../ui-admin/%23realms/{0}/scripts/edit/{1}\"  resourceName=\"oidcClaimsScript\"  syntax=\"string\"  type=\"single_choice\"  uitype=\"scriptSelect\" >\n                    <ChoiceValues>\n                        <ChoiceValuesClassName className=\"org.forgerock.openam.scripting.service.ScriptChoiceValues\" >\n                            <AttributeValuePair>\n                                <Attribute name=\"ContextId\" ></Attribute>\n                                <Value>OIDC_CLAIMS</Value>\n                            </AttributeValuePair>\n                        </ChoiceValuesClassName>\n                    </ChoiceValues>\n                    <DefaultValues>\n                        <Value>36863ffb-40ec-48b9-94b1-9a99f71cc3b5</Value>\n                    </DefaultValues>\n                </AttributeSchema>\n\n                <AttributeSchema cosQualifier=\"default\"  hideConfigUI=\"no\"  i18nKey=\"a105\"  isSearchable=\"no\"  listOrder=\"natural\"  name=\"forgerock-oauth2-provider-response-type-map-class\"  order=\"90\"  resourceName=\"responseTypeClasses\"  syntax=\"string\"  type=\"list\" >\n                    <DefaultValues>\n                        <Value>device_code|org.forgerock.oauth2.core.TokenResponseTypeHandler</Value>\n                        <Value>token|org.forgerock.oauth2.core.TokenResponseTypeHandler</Value>\n                        <Value>code|org.forgerock.oauth2.core.AuthorizationCodeResponseTypeHandler</Value>\n                    </DefaultValues>\n                </AttributeSchema>\n\n                <AttributeSchema cosQualifier=\"default\"  hideConfigUI=\"no\"  i18nKey=\"a106\"  isSearchable=\"no\"  listOrder=\"natural\"  name=\"forgerock-oauth2-provider-authentication-attributes\"  order=\"100\"  resourceName=\"authenticationAttributes\"  syntax=\"string\"  type=\"list\" >\n                    <DefaultValues>\n                        <Value>uid</Value>\n                    </DefaultValues>\n                </AttributeSchema>\n\n                <AttributeSchema cosQualifier=\"default\"  hideConfigUI=\"no\"  i18nKey=\"a107\"  isSearchable=\"no\"  listOrder=\"natural\"  name=\"forgerock-oauth2-provider-saved-consent-attribute\"  order=\"110\"  resourceName=\"savedConsentAttribute\"  syntax=\"string\"  type=\"single\" >\n                    <IsOptional></IsOptional>\n                    <DefaultValues>\n                        <Value></Value>\n                    </DefaultValues>\n                </AttributeSchema>\n\n                <AttributeSchema cosQualifier=\"default\"  hideConfigUI=\"no\"  i18nKey=\"a1075\"  isSearchable=\"no\"  listOrder=\"natural\"  name=\"displayNameAttribute\"  order=\"120\"  syntax=\"string\"  type=\"single\" >\n                    <DefaultValues>\n                        <Value>cn</Value>\n                    </DefaultValues>\n                </AttributeSchema>\n\n                <AttributeSchema cosQualifier=\"default\"  hideConfigUI=\"no\"  i18nKey=\"a108\"  isSearchable=\"no\"  listOrder=\"natural\"  name=\"forgerock-oauth2-provider-supported-scopes\"  order=\"130\"  resourceName=\"supportedScopes\"  syntax=\"string\"  type=\"list\" >\n                </AttributeSchema>\n\n                <AttributeSchema cosQualifier=\"default\"  hideConfigUI=\"no\"  i18nKey=\"a109\"  isSearchable=\"no\"  listOrder=\"natural\"  name=\"forgerock-oauth2-provider-jkws-uri\"  order=\"140\"  resourceName=\"jkwsURI\"  syntax=\"string\"  type=\"single\" >\n                    <IsOptional></IsOptional>\n                </AttributeSchema>\n\n                <AttributeSchema cosQualifier=\"default\"  hideConfigUI=\"no\"  i18nKey=\"a110\"  isSearchable=\"no\"  listOrder=\"natural\"  name=\"forgerock-oauth2-provider-subject-types-supported\"  order=\"150\"  resourceName=\"supportedSubjectTypes\"  syntax=\"string\"  type=\"list\" >\n                    <DefaultValues>\n                        <Value>public</Value>\n                    </DefaultValues>\n                </AttributeSchema>\n\n                <AttributeSchema cosQualifier=\"default\"  hideConfigUI=\"no\"  i18nKey=\"a111\"  isSearchable=\"no\"  listOrder=\"natural\"  name=\"forgerock-oauth2-provider-id-token-signing-algorithms-supported\"  order=\"160\"  resourceName=\"supportedIDTokenSigningAlgorithms\"  syntax=\"string\"  type=\"list\" >\n                    <DefaultValues>\n                        <Value>HS256</Value>\n                        <Value>HS384</Value>\n                        <Value>HS512</Value>\n                        <Value>RS256</Value>\n                        <Value>RS384</Value>\n                        <Value>RS512</Value>\n                        <Value>ES256</Value>\n                        <Value>ES384</Value>\n                        <Value>ES512</Value>\n                        <Value>PS256</Value>\n                        <Value>PS384</Value>\n                        <Value>PS512</Value>\n                    </DefaultValues>\n                </AttributeSchema>\n                <AttributeSchema cosQualifier=\"default\"  hideConfigUI=\"no\"  i18nKey=\"a111a\"  isSearchable=\"no\"  listOrder=\"natural\"  name=\"supportedIDTokenEncryptionAlgorithms\"  order=\"170\"  syntax=\"string\"  type=\"list\" >\n                    <DefaultValues>\n                        <Value>RSA1_5</Value>\n                        <Value>RSA-OAEP</Value>\n                        <Value>RSA-OAEP-256</Value>\n                        <Value>dir</Value>\n                        <Value>A128KW</Value>\n                        <Value>A192KW</Value>\n                        <Value>A256KW</Value>\n                    </DefaultValues>\n                </AttributeSchema>\n                <AttributeSchema cosQualifier=\"default\"  hideConfigUI=\"no\"  i18nKey=\"a111b\"  isSearchable=\"no\"  listOrder=\"natural\"  name=\"supportedIDTokenEncryptionMethods\"  order=\"180\"  syntax=\"string\"  type=\"list\" >\n                    <DefaultValues>\n                        <Value>A128CBC-HS256</Value>\n                        <Value>A192CBC-HS384</Value>\n                        <Value>A256CBC-HS512</Value>\n                        <Value>A128GCM</Value>\n                        <Value>A192GCM</Value>\n                        <Value>A256GCM</Value>\n                    </DefaultValues>\n                </AttributeSchema>\n                <AttributeSchema cosQualifier=\"default\"  hideConfigUI=\"no\"  i18nKey=\"a112\"  isSearchable=\"no\"  listOrder=\"natural\"  name=\"forgerock-oauth2-provider-supported-claims\"  order=\"190\"  resourceName=\"supportedClaims\"  syntax=\"string\"  type=\"list\" >\n                    <IsOptional></IsOptional>\n                </AttributeSchema>\n\n                <AttributeSchema cosQualifier=\"default\"  hideConfigUI=\"no\"  i18nKey=\"a122\"  isSearchable=\"no\"  listOrder=\"natural\"  name=\"forgerock-oauth2-provider-default-scopes\"  order=\"200\"  resourceName=\"defaultScopes\"  syntax=\"string\"  type=\"list\" >\n                    <IsOptional></IsOptional>\n                </AttributeSchema>\n\n                <AttributeSchema cosQualifier=\"default\"  hideConfigUI=\"no\"  i18nKey=\"a113\"  isSearchable=\"no\"  listOrder=\"natural\"  name=\"forgerock-oauth2-provider-jwt-token-lifetime\"  order=\"210\"  rangeEnd=\"2147483647\"  rangeStart=\"0\"  resourceName=\"jwtTokenLifetime\"  syntax=\"number_range\"  type=\"single\"  validator=\"RequiredValueValidator\" >\n                    <IsOptional></IsOptional>\n                    <DefaultValues>\n                        <Value>3600</Value>\n                    </DefaultValues>\n                </AttributeSchema>\n                <AttributeSchema cosQualifier=\"default\"  hideConfigUI=\"no\"  i18nKey=\"a113a\"  isSearchable=\"no\"  listOrder=\"insertion\"  name=\"tokenSigningAlgorithm\"  order=\"220\"  syntax=\"string\"  type=\"single_choice\" >\n                    <ChoiceValues>\n                        <ChoiceValue i18nKey=\"choiceHS256\" >HS256</ChoiceValue>\n                        <ChoiceValue i18nKey=\"choiceHS384\" >HS384</ChoiceValue>\n                        <ChoiceValue i18nKey=\"choiceHS512\" >HS512</ChoiceValue>\n                        <ChoiceValue i18nKey=\"choiceRS256\" >RS256</ChoiceValue>\n                        <ChoiceValue i18nKey=\"choiceRS384\" >RS384</ChoiceValue>\n                        <ChoiceValue i18nKey=\"choiceRS512\" >RS512</ChoiceValue>\n                        <ChoiceValue i18nKey=\"choiceES256\" >ES256</ChoiceValue>\n                        <ChoiceValue i18nKey=\"choiceES384\" >ES384</ChoiceValue>\n                        <ChoiceValue i18nKey=\"choiceES512\" >ES512</ChoiceValue>\n                        <ChoiceValue i18nKey=\"choicePS256\" >PS256</ChoiceValue>\n                        <ChoiceValue i18nKey=\"choicePS384\" >PS384</ChoiceValue>\n                        <ChoiceValue i18nKey=\"choicePS512\" >PS512</ChoiceValue>\n                    </ChoiceValues>\n                    <DefaultValues>\n                        <Value>HS256</Value>\n                    </DefaultValues>\n                </AttributeSchema>\n                <AttributeSchema cosQualifier=\"default\"  hideConfigUI=\"no\"  i18nKey=\"a138\"  isSearchable=\"no\"  listOrder=\"natural\"  name=\"tokenCompressionEnabled\"  order=\"223\"  syntax=\"boolean\"  type=\"single\" >\n                    <BooleanValues>\n                        <BooleanTrueValue i18nKey=\"i18nTrue\" >true</BooleanTrueValue>\n                        <BooleanFalseValue i18nKey=\"i18nFalse\" >false</BooleanFalseValue>\n                    </BooleanValues>\n                </AttributeSchema>\n                <AttributeSchema cosQualifier=\"default\"  hideConfigUI=\"no\"  i18nKey=\"a137\"  isSearchable=\"no\"  listOrder=\"natural\"  name=\"idTokenInfoClientAuthenticationEnabled\"  order=\"225\"  syntax=\"boolean\"  type=\"single\" >\n                    <BooleanValues>\n                        <BooleanTrueValue i18nKey=\"i18nTrue\" >true</BooleanTrueValue>\n                        <BooleanFalseValue i18nKey=\"i18nFalse\" >false</BooleanFalseValue>\n                    </BooleanValues>\n                    <DefaultValues>\n                        <Value>true</Value>\n                    </DefaultValues>\n                </AttributeSchema>\n\n                <AttributeSchema cosQualifier=\"default\"  hideConfigUI=\"no\"  i18nKey=\"tokenEncryptionEnabled\"  isSearchable=\"no\"  listOrder=\"natural\"  name=\"tokenEncryptionEnabled\"  order=\"242\"  syntax=\"boolean\"  type=\"single\" >\n                    <BooleanValues>\n                        <BooleanTrueValue i18nKey=\"i18nTrue\" >true</BooleanTrueValue>\n                        <BooleanFalseValue i18nKey=\"i18nFalse\" >false</BooleanFalseValue>\n                    </BooleanValues>\n                    <DefaultValues>\n                        <Value>false</Value>\n                    </DefaultValues>\n                </AttributeSchema>\n\n                <AttributeSchema cosQualifier=\"default\"  hideConfigUI=\"no\"  i18nKey=\"a123\"  isSearchable=\"no\"  listOrder=\"natural\"  name=\"forgerock-oauth2-provider-claims-parameter-supported\"  order=\"250\"  resourceName=\"claimsParameterSupported\"  syntax=\"boolean\"  type=\"single\" >\n                    <BooleanValues>\n                        <BooleanTrueValue i18nKey=\"i18nTrue\" >true</BooleanTrueValue>\n                        <BooleanFalseValue i18nKey=\"i18nFalse\" >false</BooleanFalseValue>\n                    </BooleanValues>\n                    <DefaultValues>\n                        <Value>false</Value>\n                    </DefaultValues>\n                </AttributeSchema>\n\n                <AttributeSchema cosQualifier=\"default\"  hideConfigUI=\"no\"  i18nKey=\"a124\"  isSearchable=\"no\"  listOrder=\"natural\"  name=\"forgerock-oauth2-provider-hash-salt\"  order=\"260\"  resourceName=\"hashSalt\"  syntax=\"string\"  type=\"single\" >\n                    <IsOptional></IsOptional>\n                    <ExampleValue>\n                        <Value>changeme</Value>\n                    </ExampleValue>\n                </AttributeSchema>\n\n                <AttributeSchema cosQualifier=\"default\"  hideConfigUI=\"no\"  i18nKey=\"a126\"  isSearchable=\"no\"  listOrder=\"natural\"  name=\"forgerock-oauth2-provider-code-verifier-enforced\"  order=\"270\"  resourceName=\"codeVerifierEnforced\"  syntax=\"string\"  type=\"single_choice\" >\n                    <ChoiceValues>\n                        <ChoiceValue i18nKey=\"codeVerifier.3.always\" >true</ChoiceValue>\n                        <ChoiceValue i18nKey=\"codeVerifier.2.public\" >public</ChoiceValue>\n                        <ChoiceValue i18nKey=\"codeVerifier.1.passwordless\" >passwordless</ChoiceValue>\n                        <ChoiceValue i18nKey=\"codeVerifier.0.never\" >false</ChoiceValue>\n                    </ChoiceValues>\n                    <DefaultValues>\n                        <Value>false</Value>\n                    </DefaultValues>\n                </AttributeSchema>\n\n                <AttributeSchema cosQualifier=\"default\"  hideConfigUI=\"no\"  i18nKey=\"a115a\"  isSearchable=\"no\"  listOrder=\"natural\"  name=\"dynamicClientRegistrationSoftwareStatementRequired\"  order=\"271\"  syntax=\"boolean\"  type=\"single\" >\n\n                <BooleanValues>\n                        <BooleanTrueValue i18nKey=\"i18nTrue\" >true</BooleanTrueValue>\n                        <BooleanFalseValue i18nKey=\"i18nFalse\" >false</BooleanFalseValue>\n                    </BooleanValues>\n                    <DefaultValues>\n                        <Value>false</Value>\n                    </DefaultValues>\n                </AttributeSchema>\n\n                <AttributeSchema cosQualifier=\"default\"  hideConfigUI=\"no\"  i18nKey=\"a115b\"  isSearchable=\"no\"  listOrder=\"natural\"  name=\"requiredSoftwareStatementAttestedAttributes\"  order=\"272\"  syntax=\"string\"  type=\"list\" >\n                    <DefaultValues>\n                        <Value>redirect_uris</Value>\n                    </DefaultValues>\n                </AttributeSchema>\n\n                <AttributeSchema cosQualifier=\"default\"  hideConfigUI=\"no\"  i18nKey=\"a115\"  isSearchable=\"no\"  listOrder=\"natural\"  name=\"forgerock-oauth2-provider-allow-open-dynamic-registration\"  order=\"280\"  resourceName=\"allowDynamicRegistration\"  syntax=\"boolean\"  type=\"single\" >\n                    <BooleanValues>\n                        <BooleanTrueValue i18nKey=\"i18nTrue\" >true</BooleanTrueValue>\n                        <BooleanFalseValue i18nKey=\"i18nFalse\" >false</BooleanFalseValue>\n                    </BooleanValues>\n                    <DefaultValues>\n                        <Value>false</Value>\n                    </DefaultValues>\n                </AttributeSchema>\n\n                <AttributeSchema cosQualifier=\"default\"  hideConfigUI=\"no\"  i18nKey=\"a116\"  isSearchable=\"no\"  listOrder=\"natural\"  name=\"forgerock-oauth2-provider-generate-registration-access-tokens\"  order=\"290\"  resourceName=\"generateRegistrationAccessTokens\"  syntax=\"boolean\"  type=\"single\" >\n                    <BooleanValues>\n                        <BooleanTrueValue i18nKey=\"i18nTrue\" >true</BooleanTrueValue>\n                        <BooleanFalseValue i18nKey=\"i18nFalse\" >false</BooleanFalseValue>\n                    </BooleanValues>\n                    <DefaultValues>\n                        <Value>true</Value>\n                    </DefaultValues>\n                </AttributeSchema>\n\n\n                <AttributeSchema cosQualifier=\"default\"  hideConfigUI=\"no\"  isSearchable=\"no\"  listOrder=\"natural\"  name=\"MapValueValidator\"  order=\"300\"  syntax=\"string\"  type=\"validator\" >\n                    <DefaultValues>\n                        <Value>com.sun.identity.common.configuration.MapValueValidator</Value>\n                    </DefaultValues>\n                </AttributeSchema>\n\n                <AttributeSchema cosQualifier=\"default\"  hideConfigUI=\"no\"  i18nKey=\"a117\"  isSearchable=\"no\"  listOrder=\"natural\"  name=\"forgerock-oauth2-provider-loa-mapping\"  order=\"310\"  resourceName=\"loaMapping\"  syntax=\"string\"  type=\"list\"  uitype=\"maplist\"  validator=\"MapValueValidator\" >\n                    <IsOptional></IsOptional>\n                    <ChoiceValues>\n                        <ChoiceValuesClassName className=\"com.sun.identity.authentication.service.ConfiguredAuthServices\" ></ChoiceValuesClassName>\n                    </ChoiceValues>\n                </AttributeSchema>\n\n                <AttributeSchema cosQualifier=\"default\"  hideConfigUI=\"no\"  isSearchable=\"no\"  listOrder=\"natural\"  name=\"ListValueValidator\"  order=\"315\"  syntax=\"string\"  type=\"validator\" >\n                    <DefaultValues>\n                        <Value>com.sun.identity.common.configuration.ListValueValidator</Value>\n                    </DefaultValues>\n                </AttributeSchema>\n\n                <AttributeSchema cosQualifier=\"default\"  hideConfigUI=\"no\"  i18nKey=\"a118\"  isSearchable=\"no\"  listOrder=\"natural\"  name=\"forgerock-oauth2-provider-default-acr\"  order=\"320\"  resourceName=\"defaultACR\"  syntax=\"string\"  type=\"list\"  uitype=\"orderedlist\"  validator=\"ListValueValidator\" >\n                    <IsOptional></IsOptional>\n                </AttributeSchema>\n\n                <AttributeSchema cosQualifier=\"default\"  hideConfigUI=\"no\"  i18nKey=\"a119\"  isSearchable=\"no\"  listOrder=\"natural\"  name=\"forgerock-oauth2-provider-amr-mappings\"  order=\"330\"  resourceName=\"amrMappings\"  syntax=\"string\"  type=\"list\"  uitype=\"maplist\"  validator=\"MapValueValidator\" >\n                    <IsOptional></IsOptional>\n                    <ChoiceValues>\n                        <ChoiceValuesClassName className=\"com.sun.identity.authentication.service.AllConfiguredModuleInstances\" ></ChoiceValuesClassName>\n                    </ChoiceValues>\n                </AttributeSchema>\n\n                <AttributeSchema cosQualifier=\"default\"  hideConfigUI=\"no\"  i18nKey=\"a120\"  isSearchable=\"no\"  listOrder=\"natural\"  name=\"forgerock-oauth2-provider-modified-attribute-name\"  order=\"340\"  resourceName=\"modifiedTimestampAttribute\"  syntax=\"string\"  type=\"single\" >\n                    <IsOptional></IsOptional>\n                </AttributeSchema>\n\n                <AttributeSchema cosQualifier=\"default\"  hideConfigUI=\"no\"  i18nKey=\"a121\"  isSearchable=\"no\"  listOrder=\"natural\"  name=\"forgerock-oauth2-provider-created-attribute-name\"  order=\"350\"  resourceName=\"createdTimestampAttribute\"  syntax=\"string\"  type=\"single\" >\n                    <IsOptional></IsOptional>\n                </AttributeSchema>\n\n                <AttributeSchema cosQualifier=\"default\"  hideConfigUI=\"no\"  i18nKey=\"a125\"  isSearchable=\"no\"  listOrder=\"natural\"  name=\"alwaysAddClaimsToToken\"  order=\"360\"  syntax=\"boolean\"  type=\"single\" >\n                    <BooleanValues>\n                        <BooleanTrueValue i18nKey=\"i18nTrue\" >true</BooleanTrueValue>\n                        <BooleanFalseValue i18nKey=\"i18nFalse\" >false</BooleanFalseValue>\n                    </BooleanValues>\n                    <DefaultValues>\n                        <Value>false</Value>\n                    </DefaultValues>\n                </AttributeSchema>\n\n                <AttributeSchema cosQualifier=\"default\"  hideConfigUI=\"no\"  i18nKey=\"a127\"  isSearchable=\"no\"  listOrder=\"natural\"  name=\"verificationUrl\"  order=\"370\"  syntax=\"string\"  type=\"single\" >\n                    <IsOptional></IsOptional>\n                </AttributeSchema>\n\n                <AttributeSchema cosQualifier=\"default\"  hideConfigUI=\"no\"  i18nKey=\"a128\"  isSearchable=\"no\"  listOrder=\"natural\"  name=\"completionUrl\"  order=\"380\"  syntax=\"string\"  type=\"single\" >\n                    <IsOptional></IsOptional>\n                </AttributeSchema>\n\n                <AttributeSchema cosQualifier=\"default\"  hideConfigUI=\"no\"  i18nKey=\"a129\"  isSearchable=\"no\"  listOrder=\"natural\"  name=\"deviceCodeLifetime\"  order=\"390\"  rangeEnd=\"2147483647\"  rangeStart=\"0\"  syntax=\"number_range\"  type=\"single\" >\n                    <DefaultValues>\n                        <Value>300</Value>\n                    </DefaultValues>\n                </AttributeSchema>\n\n                <AttributeSchema cosQualifier=\"default\"  hideConfigUI=\"no\"  i18nKey=\"a130\"  isSearchable=\"no\"  listOrder=\"natural\"  name=\"devicePollInterval\"  order=\"400\"  rangeEnd=\"2147483647\"  rangeStart=\"0\"  syntax=\"number_range\"  type=\"single\" >\n                    <DefaultValues>\n                        <Value>5</Value>\n                    </DefaultValues>\n                </AttributeSchema>\n\n                <AttributeSchema cosQualifier=\"default\"  hideConfigUI=\"no\"  i18nKey=\"a131\"  isSearchable=\"no\"  listOrder=\"natural\"  name=\"storeOpsTokens\"  order=\"410\"  syntax=\"boolean\"  type=\"single\" >\n                    <BooleanValues>\n                        <BooleanTrueValue i18nKey=\"i18nTrue\" >true</BooleanTrueValue>\n                        <BooleanFalseValue i18nKey=\"i18nFalse\" >false</BooleanFalseValue>\n                    </BooleanValues>\n                    <DefaultValues>\n                        <Value>true</Value>\n                    </DefaultValues>\n                </AttributeSchema>\n\n                <AttributeSchema cosQualifier=\"default\"  hideConfigUI=\"no\"  i18nKey=\"a132\"  isSearchable=\"no\"  listOrder=\"natural\"  name=\"clientsCanSkipConsent\"  order=\"420\"  syntax=\"boolean\"  type=\"single\" >\n                    <BooleanValues>\n                        <BooleanTrueValue i18nKey=\"i18nTrue\" >true</BooleanTrueValue>\n                        <BooleanFalseValue i18nKey=\"i18nFalse\" >false</BooleanFalseValue>\n                    </BooleanValues>\n                    <DefaultValues>\n                        <Value>false</Value>\n                    </DefaultValues>\n                </AttributeSchema>\n\n                <AttributeSchema cosQualifier=\"default\"  hideConfigUI=\"no\"  i18nKey=\"passwordGrantAuthService\"  isSearchable=\"no\"  listOrder=\"natural\"  name=\"passwordGrantAuthService\"  order=\"430\"  syntax=\"string\"  type=\"single_choice\" >\n                    <ChoiceValues>\n                        <ChoiceValuesClassName className=\"com.sun.identity.authentication.service.ConfiguredAuthServices\" ></ChoiceValuesClassName>\n                    </ChoiceValues>\n                </AttributeSchema>\n\n                <AttributeSchema cosQualifier=\"default\"  hideConfigUI=\"no\"  i18nKey=\"a140\"  isSearchable=\"no\"  listOrder=\"natural\"  name=\"moduleMessageEnabledInPasswordGrant\"  order=\"440\"  syntax=\"boolean\"  type=\"single\" >\n                    <BooleanValues>\n                        <BooleanTrueValue i18nKey=\"i18nTrue\" >true</BooleanTrueValue>\n                        <BooleanFalseValue i18nKey=\"i18nFalse\" >false</BooleanFalseValue>\n                    </BooleanValues>\n                    <DefaultValues>\n                        <Value>false</Value>\n                    </DefaultValues>\n                </AttributeSchema>\n                <AttributeSchema cosQualifier=\"default\"  hideConfigUI=\"no\"  i18nKey=\"a142\"  isSearchable=\"no\"  listOrder=\"natural\"  name=\"supportedRequestParameterSigningAlgorithms\"  order=\"442\"  syntax=\"string\"  type=\"list\" >\n                    <DefaultValues>\n                        <Value>HS256</Value>\n                        <Value>HS384</Value>\n                        <Value>HS512</Value>\n                        <Value>RS256</Value>\n                        <Value>RS384</Value>\n                        <Value>RS512</Value>\n                        <Value>ES256</Value>\n                        <Value>ES384</Value>\n                        <Value>ES512</Value>\n                        <Value>PS256</Value>\n                        <Value>PS384</Value>\n                        <Value>PS512</Value>\n                    </DefaultValues>\n                </AttributeSchema>\n                <AttributeSchema cosQualifier=\"default\"  hideConfigUI=\"no\"  i18nKey=\"a143\"  isSearchable=\"no\"  listOrder=\"natural\"  name=\"supportedRequestParameterEncryptionAlgorithms\"  order=\"443\"  syntax=\"string\"  type=\"list\" >\n                    <DefaultValues>\n                        <Value>RSA1_5</Value>\n                        <Value>RSA-OAEP</Value>\n                        <Value>RSA-OAEP-256</Value>\n                        <Value>dir</Value>\n                        <Value>A128KW</Value>\n                        <Value>A192KW</Value>\n                        <Value>A256KW</Value>\n                    </DefaultValues>\n                </AttributeSchema>\n                <AttributeSchema cosQualifier=\"default\"  hideConfigUI=\"no\"  i18nKey=\"a144\"  isSearchable=\"no\"  listOrder=\"natural\"  name=\"supportedRequestParameterEncryptionEnc\"  order=\"444\"  syntax=\"string\"  type=\"list\" >\n                    <DefaultValues>\n                        <Value>A128CBC-HS256</Value>\n                        <Value>A192CBC-HS384</Value>\n                        <Value>A256CBC-HS512</Value>\n                        <Value>A128GCM</Value>\n                        <Value>A192GCM</Value>\n                        <Value>A256GCM</Value>\n                    </DefaultValues>\n                </AttributeSchema>\n                <AttributeSchema cosQualifier=\"default\"  hideConfigUI=\"no\"  i18nKey=\"supportedTokenEndpointAuthenticationSigningAlgorithms\"  isSearchable=\"no\"  listOrder=\"natural\"  name=\"supportedTokenEndpointAuthenticationSigningAlgorithms\"  order=\"445\"  syntax=\"string\"  type=\"list\" >\n                    <DefaultValues>\n                        <Value>HS256</Value>\n                        <Value>HS384</Value>\n                        <Value>HS512</Value>\n                        <Value>RS256</Value>\n                        <Value>RS384</Value>\n                        <Value>RS512</Value>\n                        <Value>ES256</Value>\n                        <Value>ES384</Value>\n                        <Value>ES512</Value>\n                        <Value>PS256</Value>\n                        <Value>PS384</Value>\n                        <Value>PS512</Value>\n                    </DefaultValues>\n                </AttributeSchema>\n                <AttributeSchema cosQualifier=\"default\"  hideConfigUI=\"no\"  i18nKey=\"a146\"  isSearchable=\"no\"  listOrder=\"natural\"  name=\"authorisedOpenIdConnectSSOClients\"  order=\"446\"  syntax=\"string\"  type=\"list\" >\n                </AttributeSchema>\n                <AttributeSchema cosQualifier=\"default\"  hideConfigUI=\"no\"  i18nKey=\"a147\"  isSearchable=\"no\"  listOrder=\"natural\"  name=\"enableRemoteConsent\"  order=\"447\"  syntax=\"boolean\"  type=\"single\" >\n                    <BooleanValues>\n                        <BooleanTrueValue i18nKey=\"i18nTrue\" >true</BooleanTrueValue>\n                        <BooleanFalseValue i18nKey=\"i18nFalse\" >false</BooleanFalseValue>\n                    </BooleanValues>\n                    <DefaultValues>\n                        <Value>false</Value>\n                    </DefaultValues>\n                </AttributeSchema>\n                <AttributeSchema cosQualifier=\"default\"  hideConfigUI=\"no\"  i18nKey=\"a148\"  isSearchable=\"no\"  listOrder=\"natural\"  name=\"remoteConsentServiceId\"  order=\"448\"  syntax=\"string\"  type=\"single_choice\" >\n                    <IsOptional></IsOptional>\n                    <ChoiceValues>\n                        <ChoiceValuesClassName className=\"org.forgerock.openam.oauth2.remoteconsent.RemoteConsentAgentChoiceValues\" ></ChoiceValuesClassName>\n                    </ChoiceValues>\n                </AttributeSchema>\n                <AttributeSchema cosQualifier=\"default\"  hideConfigUI=\"no\"  i18nKey=\"a149\"  isSearchable=\"no\"  listOrder=\"natural\"  name=\"supportedRcsRequestSigningAlgorithms\"  order=\"449\"  syntax=\"string\"  type=\"list\" >\n                    <DefaultValues>\n                        <Value>HS256</Value>\n                        <Value>HS384</Value>\n                        <Value>HS512</Value>\n                        <Value>RS256</Value>\n                        <Value>RS384</Value>\n                        <Value>RS512</Value>\n                        <Value>ES256</Value>\n                        <Value>ES384</Value>\n                        <Value>ES512</Value>\n                        <Value>PS256</Value>\n                        <Value>PS384</Value>\n                        <Value>PS512</Value>\n                    </DefaultValues>\n                </AttributeSchema>\n                <AttributeSchema cosQualifier=\"default\"  hideConfigUI=\"no\"  i18nKey=\"a150\"  isSearchable=\"no\"  listOrder=\"natural\"  name=\"supportedRcsRequestEncryptionAlgorithms\"  order=\"450\"  syntax=\"string\"  type=\"list\" >\n                    <DefaultValues>\n                        <Value>RSA1_5</Value>\n                        <Value>RSA-OAEP</Value>\n                        <Value>RSA-OAEP-256</Value>\n                        <Value>dir</Value>\n                        <Value>A128KW</Value>\n                        <Value>A192KW</Value>\n                        <Value>A256KW</Value>\n                    </DefaultValues>\n                </AttributeSchema>\n                <AttributeSchema cosQualifier=\"default\"  hideConfigUI=\"no\"  i18nKey=\"a151\"  isSearchable=\"no\"  listOrder=\"natural\"  name=\"supportedRcsRequestEncryptionMethods\"  order=\"451\"  syntax=\"string\"  type=\"list\" >\n                    <DefaultValues>\n                        <Value>A128CBC-HS256</Value>\n                        <Value>A192CBC-HS384</Value>\n                        <Value>A256CBC-HS512</Value>\n                        <Value>A128GCM</Value>\n                        <Value>A192GCM</Value>\n                        <Value>A256GCM</Value>\n                    </DefaultValues>\n                </AttributeSchema>\n                <AttributeSchema cosQualifier=\"default\"  hideConfigUI=\"no\"  i18nKey=\"a152\"  isSearchable=\"no\"  listOrder=\"natural\"  name=\"supportedRcsResponseSigningAlgorithms\"  order=\"452\"  syntax=\"string\"  type=\"list\" >\n                    <DefaultValues>\n                        <Value>HS256</Value>\n                        <Value>HS384</Value>\n                        <Value>HS512</Value>\n                        <Value>RS256</Value>\n                        <Value>RS384</Value>\n                        <Value>RS512</Value>\n                        <Value>ES256</Value>\n                        <Value>ES384</Value>\n                        <Value>ES512</Value>\n                        <Value>PS256</Value>\n                        <Value>PS384</Value>\n                        <Value>PS512</Value>\n                    </DefaultValues>\n                </AttributeSchema>\n                <AttributeSchema cosQualifier=\"default\"  hideConfigUI=\"no\"  i18nKey=\"a153\"  isSearchable=\"no\"  listOrder=\"natural\"  name=\"supportedRcsResponseEncryptionAlgorithms\"  order=\"453\"  syntax=\"string\"  type=\"list\" >\n                    <DefaultValues>\n                        <Value>RSA1_5</Value>\n                        <Value>RSA-OAEP</Value>\n                        <Value>RSA-OAEP-256</Value>\n                        <Value>dir</Value>\n                        <Value>A128KW</Value>\n                        <Value>A192KW</Value>\n                        <Value>A256KW</Value>\n                    </DefaultValues>\n                </AttributeSchema>\n                <AttributeSchema cosQualifier=\"default\"  hideConfigUI=\"no\"  i18nKey=\"a154\"  isSearchable=\"no\"  listOrder=\"natural\"  name=\"supportedRcsResponseEncryptionMethods\"  order=\"454\"  syntax=\"string\"  type=\"list\" >\n                    <DefaultValues>\n                        <Value>A128CBC-HS256</Value>\n                        <Value>A192CBC-HS384</Value>\n                        <Value>A256CBC-HS512</Value>\n                        <Value>A128GCM</Value>\n                        <Value>A192GCM</Value>\n                        <Value>A256GCM</Value>\n                    </DefaultValues>\n                </AttributeSchema>\n                <AttributeSchema cosQualifier=\"default\"  hideConfigUI=\"no\"  i18nKey=\"usePolicyEngineForScope\"  isSearchable=\"no\"  listOrder=\"natural\"  name=\"usePolicyEngineForScope\"  order=\"55\"  syntax=\"boolean\"  type=\"single\" >\n                    <BooleanValues>\n                        <BooleanTrueValue i18nKey=\"i18nTrue\" >true</BooleanTrueValue>\n                        <BooleanFalseValue i18nKey=\"i18nFalse\" >false</BooleanFalseValue>\n                    </BooleanValues>\n                    <DefaultValues>\n                        <Value>false</Value>\n                    </DefaultValues>\n                </AttributeSchema>\n\n                <AttributeSchema cosQualifier=\"default\"  hideConfigUI=\"no\"  i18nKey=\"a155\"  isSearchable=\"no\"  listOrder=\"natural\"  name=\"dynamicClientRegistrationScope\"  order=\"455\"  syntax=\"string\"  type=\"single\" >\n                    <DefaultValues>\n                        <Value>dynamic_client_registration</Value>\n                    </DefaultValues>\n                </AttributeSchema>\n\n                <AttributeSchema cosQualifier=\"default\"  hideConfigUI=\"no\"  i18nKey=\"a156\"  isSearchable=\"no\"  listOrder=\"natural\"  name=\"supportedUserInfoSigningAlgorithms\"  order=\"456\"  syntax=\"string\"  type=\"list\" >\n                    <DefaultValues>\n                        <Value>HS256</Value>\n                        <Value>HS384</Value>\n                        <Value>HS512</Value>\n                        <Value>RS256</Value>\n                        <Value>ES256</Value>\n                        <Value>ES384</Value>\n                        <Value>ES512</Value>\n                    </DefaultValues>\n                </AttributeSchema>\n                <AttributeSchema cosQualifier=\"default\"  hideConfigUI=\"no\"  i18nKey=\"a157\"  isSearchable=\"no\"  listOrder=\"natural\"  name=\"supportedUserInfoEncryptionAlgorithms\"  order=\"457\"  syntax=\"string\"  type=\"list\" >\n                    <DefaultValues>\n                        <Value>RSA-OAEP</Value>\n                        <Value>RSA-OAEP-256</Value>\n                        <Value>A128KW</Value>\n                        <Value>A256KW</Value>\n                        <Value>RSA1_5</Value>\n                        <Value>dir</Value>\n                        <Value>A192KW</Value>\n                    </DefaultValues>\n                </AttributeSchema>\n                <AttributeSchema cosQualifier=\"default\"  hideConfigUI=\"no\"  i18nKey=\"a158\"  isSearchable=\"no\"  listOrder=\"natural\"  name=\"supportedUserInfoEncryptionEnc\"  order=\"458\"  syntax=\"string\"  type=\"list\" >\n                    <DefaultValues>\n                        <Value>A128CBC-HS256</Value>\n                        <Value>A192CBC-HS384</Value>\n                        <Value>A256CBC-HS512</Value>\n                        <Value>A128GCM</Value>\n                        <Value>A192GCM</Value>\n                        <Value>A256GCM</Value>\n                    </DefaultValues>\n                </AttributeSchema>\n\n                <AttributeSchema cosQualifier=\"default\"  hideConfigUI=\"no\"  i18nKey=\"supportedTokenIntrospectionResponseSigningAlgorithms\"  isSearchable=\"no\"  listOrder=\"natural\"  name=\"supportedTokenIntrospectionResponseSigningAlgorithms\"  order=\"459\"  syntax=\"string\"  type=\"list\" >\n                    <ChoiceValues>\n                        <ChoiceValue>HS256</ChoiceValue>\n                        <ChoiceValue>HS384</ChoiceValue>\n                        <ChoiceValue>HS512</ChoiceValue>\n                        <ChoiceValue>RS256</ChoiceValue>\n                        <ChoiceValue>RS384</ChoiceValue>\n                        <ChoiceValue>RS512</ChoiceValue>\n                        <ChoiceValue>ES256</ChoiceValue>\n                        <ChoiceValue>ES384</ChoiceValue>\n                        <ChoiceValue>ES512</ChoiceValue>\n                        <ChoiceValue>PS256</ChoiceValue>\n                        <ChoiceValue>PS384</ChoiceValue>\n                        <ChoiceValue>PS512</ChoiceValue>\n                        <ChoiceValue>EdDSA</ChoiceValue>\n                    </ChoiceValues>\n                    <DefaultValues>\n                        <Value>HS256</Value>\n                        <Value>HS384</Value>\n                        <Value>HS512</Value>\n                        <Value>RS256</Value>\n                        <Value>RS384</Value>\n                        <Value>RS512</Value>\n                        <Value>ES256</Value>\n                        <Value>ES384</Value>\n                        <Value>ES512</Value>\n                        <Value>PS256</Value>\n                        <Value>PS384</Value>\n                        <Value>PS512</Value>\n                        <Value>EdDSA</Value>\n                    </DefaultValues>\n                </AttributeSchema>\n                <AttributeSchema cosQualifier=\"default\"  hideConfigUI=\"no\"  i18nKey=\"supportedTokenIntrospectionResponseEncryptionAlgorithms\"  isSearchable=\"no\"  listOrder=\"natural\"  name=\"supportedTokenIntrospectionResponseEncryptionAlgorithms\"  order=\"460\"  syntax=\"string\"  type=\"list\" >\n                    <ChoiceValues>\n                        <ChoiceValue>RSA-OAEP</ChoiceValue>\n                        <ChoiceValue>RSA-OAEP-256</ChoiceValue>\n                        <ChoiceValue>A128KW</ChoiceValue>\n                        <ChoiceValue>A256KW</ChoiceValue>\n                        <ChoiceValue>RSA1_5</ChoiceValue>\n                        <ChoiceValue>dir</ChoiceValue>\n                        <ChoiceValue>A192KW</ChoiceValue>\n                    </ChoiceValues>\n                    <DefaultValues>\n                        <Value>RSA-OAEP</Value>\n                        <Value>RSA-OAEP-256</Value>\n                        <Value>A128KW</Value>\n                        <Value>A256KW</Value>\n                        <Value>RSA1_5</Value>\n                        <Value>dir</Value>\n                        <Value>A192KW</Value>\n                    </DefaultValues>\n                </AttributeSchema>\n                <AttributeSchema cosQualifier=\"default\"  hideConfigUI=\"no\"  i18nKey=\"supportedTokenIntrospectionResponseEncryptionEnc\"  isSearchable=\"no\"  listOrder=\"natural\"  name=\"supportedTokenIntrospectionResponseEncryptionEnc\"  order=\"461\"  syntax=\"string\"  type=\"list\" >\n                    <ChoiceValues>\n                        <ChoiceValue>A128CBC-HS256</ChoiceValue>\n                        <ChoiceValue>A192CBC-HS384</ChoiceValue>\n                        <ChoiceValue>A256CBC-HS512</ChoiceValue>\n                        <ChoiceValue>A128GCM</ChoiceValue>\n                        <ChoiceValue>A192GCM</ChoiceValue>\n                        <ChoiceValue>A256GCM</ChoiceValue>\n                    </ChoiceValues>\n                    <DefaultValues>\n                        <Value>A128CBC-HS256</Value>\n                        <Value>A192CBC-HS384</Value>\n                        <Value>A256CBC-HS512</Value>\n                        <Value>A128GCM</Value>\n                        <Value>A192GCM</Value>\n                        <Value>A256GCM</Value>\n                    </DefaultValues>\n                </AttributeSchema>\n\n                <AttributeSchema cosQualifier=\"default\"  hideConfigUI=\"no\"  i18nKey=\"supportedGrantType\"  isSearchable=\"no\"  listOrder=\"natural\"  name=\"supportedGrantTypes\"  order=\"560\"  resourceName=\"grantTypes\"  syntax=\"string\"  type=\"list\" >\n                    <ChoiceValues>\n                        <ChoiceValue i18nKey=\"supportedGrantType.authCode\" >authorization_code</ChoiceValue>\n                        <ChoiceValue i18nKey=\"supportedGrantType.implicit\" >implicit</ChoiceValue>\n                        <ChoiceValue i18nKey=\"supportedGrantType.ownerPassword\" >password</ChoiceValue>\n                        <ChoiceValue i18nKey=\"supportedGrantType.clientCredentials\" >client_credentials</ChoiceValue>\n                        <ChoiceValue i18nKey=\"supportedGrantType.refreshToken\" >refresh_token</ChoiceValue>\n                        <ChoiceValue i18nKey=\"supportedGrantType.uma\" >urn:ietf:params:oauth:grant-type:uma-ticket</ChoiceValue>\n                        <ChoiceValue i18nKey=\"supportedGrantType.deviceCode\" >urn:ietf:params:oauth:grant-type:device_code</ChoiceValue>\n                        <ChoiceValue i18nKey=\"supportedGrantType.saml2\" >urn:ietf:params:oauth:grant-type:saml2-bearer</ChoiceValue>\n                        <ChoiceValue i18nKey=\"supportedGrantType.jwt\" >urn:ietf:params:oauth:grant-type:jwt-bearer</ChoiceValue>\n                        <ChoiceValue i18nKey=\"supportedGrantType.backChannel\" >urn:openid:params:grant-type:ciba</ChoiceValue>\n                    </ChoiceValues>\n                    <DefaultValues>\n                        <Value>authorization_code</Value>\n                        <Value>implicit</Value>\n                        <Value>password</Value>\n                        <Value>client_credentials</Value>\n                        <Value>refresh_token</Value>\n                        <Value>urn:ietf:params:oauth:grant-type:uma-ticket</Value>\n                        <Value>urn:ietf:params:oauth:grant-type:device_code</Value>\n                        <Value>urn:ietf:params:oauth:grant-type:saml2-bearer</Value>\n                        <Value>urn:ietf:params:oauth:grant-type:jwt-bearer</Value>\n                        <Value>urn:openid:params:grant-type:ciba</Value>\n                    </DefaultValues>\n                </AttributeSchema>\n\n                <AttributeSchema cosQualifier=\"default\"  hideConfigUI=\"no\"  i18nKey=\"a159\"  isSearchable=\"no\"  listOrder=\"natural\"  name=\"tlsClientCertificateTrustedHeader\"  order=\"600\"  syntax=\"string\"  type=\"single\" >\n                    <IsOptional></IsOptional>\n                </AttributeSchema>\n                \n                <AttributeSchema cosQualifier=\"default\"  hideConfigUI=\"no\"  i18nKey=\"a160\"  isSearchable=\"no\"  listOrder=\"natural\"  name=\"tlsCertificateBoundAccessTokensEnabled\"  order=\"610\"  syntax=\"boolean\"  type=\"single\" >\n                    <BooleanValues>\n                        <BooleanTrueValue i18nKey=\"i18nTrue\" >true</BooleanTrueValue>\n                        <BooleanFalseValue i18nKey=\"i18nFalse\" >false</BooleanFalseValue>\n                    </BooleanValues>\n                    <DefaultValues>\n                        <Value>true</Value>\n                    </DefaultValues>\n                </AttributeSchema>\n\n                <AttributeSchema cosQualifier=\"default\"  hideConfigUI=\"no\"  i18nKey=\"cibaAuthReqIdLifetime\"  isSearchable=\"no\"  listOrder=\"natural\"  name=\"forgerock-oauth2-provider-ciba-auth-req-id-lifetime\"  order=\"700\"  rangeEnd=\"2147483647\"  rangeStart=\"0\"  resourceName=\"cibaAuthReqIdLifetime\"  syntax=\"number_range\"  type=\"single\"  validator=\"RequiredValueValidator\" >\n                    <DefaultValues>\n                        <Value>600</Value>\n                    </DefaultValues>\n                </AttributeSchema>\n\n                <AttributeSchema cosQualifier=\"default\"  hideConfigUI=\"no\"  i18nKey=\"cibaMinimumPollingInterval\"  isSearchable=\"no\"  listOrder=\"natural\"  name=\"forgerock-oauth2-provider-ciba-auth-req-id-polling-interval\"  order=\"800\"  rangeEnd=\"2147483647\"  rangeStart=\"0\"  resourceName=\"cibaMinimumPollingInterval\"  syntax=\"number_range\"  type=\"single\"  validator=\"RequiredValueValidator\" >\n                    <DefaultValues>\n                        <Value>2</Value>\n                    </DefaultValues>\n                </AttributeSchema>\n\n                <AttributeSchema cosQualifier=\"default\"  hideConfigUI=\"no\"  i18nKey=\"supportedCibaSigningAlgorithms\"  isSearchable=\"no\"  listOrder=\"natural\"  name=\"forgerock-oauth2-provider-ciba-supported-signing-algorithms\"  order=\"900\"  resourceName=\"supportedCibaSigningAlgorithms\"  syntax=\"string\"  type=\"list\" >\n                    <DefaultValues>\n                        <Value>ES256</Value>\n                        <Value>PS256</Value>\n                    </DefaultValues>\n                </AttributeSchema>\n            </Organization>\n        </Schema></Service></ServicesConfiguration>",
    "_type" : {
      "_id" : "OAuth2Provider",
      "name" : "OAuth2Provider",
      "collection" : false
    },
    "_id" : "1.0"
  }
}