{
  "metadata" : {
    "realm" : null,
    "amsterVersion" : "7.0.0-SNAPSHOT",
    "entityType" : "CreateObjectNode",
    "entityId" : "1.0",
    "serviceVersion" : null,
    "uid" : "ou=1.0,ou=CreateObjectNode,ou=services,ou=am-config",
    "sunServiceID" : null,
    "objectClass" : [ "top", "sunService" ],
    "pathParams" : { },
    "ou" : null
  },
  "data" : {
    "sunServiceSchema" : "<?xml version=\"1.0\" encoding=\"UTF-8\"?>\n\n<ServicesConfiguration><Service name=\"CreateObjectNode\" version=\"1.0\"><Schema i18nFileName=\"org/forgerock/openam/auth/nodes/CreateObjectNode\"  i18nKey=\"nodeDescription\"  resourceName=\"CreateObjectNode\"  revisionNumber=\"1\"  serviceHierarchy=\"/DSAMEConfig/CreateObjectNode\" ><Organization><SubSchema i18nKey=\"nodeDescription\"  inheritance=\"multiple\"  name=\"instance\"  resourceName=\"USE-PARENT\"  validate=\"yes\" ><AttributeSchema i18nKey=\"objectType\"  name=\"objectType\"  order=\"100\"  resourceName=\"objectType\"  syntax=\"string\"  type=\"single\"  validator=\"RequiredValueValidator0\" ><DefaultValues><Value>user</Value></DefaultValues></AttributeSchema><AttributeSchema name=\"RequiredValueValidator0\"  syntax=\"string\"  type=\"validator\" ><DefaultValues><Value>com.sun.identity.sm.RequiredValueValidator</Value></DefaultValues></AttributeSchema></SubSchema></Organization></Schema></Service></ServicesConfiguration>",
    "_type" : {
      "_id" : "CreateObjectNode",
      "name" : "CreateObjectNode",
      "collection" : false
    },
    "_id" : "1.0"
  }
}