{
  "metadata": {
    "realm": "/",
    "amsterVersion": "&{version}",
    "entityType": "OTPEmailSender",
    "entityId": "secondfactorwa.otpemailsender",
    "pathParams": {}
  },
  "data": {
    "_id": "secondfactorwa.otpemailsender",
    "password": null,
    "sslOption": "SSL",
    "hostPort": 0,
    "emailAttribute": "mail",
    "smsGatewayImplementationClass": "com.sun.identity.authentication.modules.hotp.DefaultSMSGatewayImpl",
    "username": "mailServerUser",
    "_type": {
      "_id": "OneTimePasswordSmtpSenderNode",
      "name": "OTP Email Sender",
      "collection": true
    }
  }
}
