{
  "metadata" : {
    "realm" : null,
    "amsterVersion" : "7.0.0-SNAPSHOT",
    "entityType" : "ScriptingService",
    "entityId" : "default/globalScripts",
    "serviceVersion" : "24b09aa8-a51c-4ccf-a07c-9a9dd08eeefd",
    "uid" : "ou=globalScripts,ou=default,ou=GlobalConfig,ou=1.0,ou=ScriptingService,ou=services,ou=am-config",
    "sunServiceID" : "globalScripts",
    "objectClass" : [ "top", "sunServiceComponent" ],
    "pathParams" : { },
    "ou" : null
  },
  "data" : {
    "_type" : {
      "_id" : "ScriptingService",
      "name" : "ScriptingService",
      "collection" : false
    },
    "_id" : "default/globalScripts"
  }
}