{
  "metadata" : {
    "realm" : null,
    "amsterVersion" : "7.0.0-SNAPSHOT",
    "entityType" : "AttributeValueDecisionNode",
    "entityId" : "1.0",
    "serviceVersion" : null,
    "uid" : "ou=1.0,ou=AttributeValueDecisionNode,ou=services,ou=am-config",
    "sunServiceID" : null,
    "objectClass" : [ "top", "sunService" ],
    "pathParams" : { },
    "ou" : null
  },
  "data" : {
    "sunServiceSchema" : "<?xml version=\"1.0\" encoding=\"UTF-8\"?>\n\n<ServicesConfiguration><Service name=\"AttributeValueDecisionNode\" version=\"1.0\"><Schema i18nFileName=\"org/forgerock/openam/auth/nodes/AttributeValueDecisionNode\"  i18nKey=\"nodeDescription\"  resourceName=\"AttributeValueDecisionNode\"  revisionNumber=\"1\"  serviceHierarchy=\"/DSAMEConfig/AttributeValueDecisionNode\" ><Organization><SubSchema i18nKey=\"nodeDescription\"  inheritance=\"multiple\"  name=\"instance\"  resourceName=\"USE-PARENT\"  validate=\"yes\" ><AttributeSchema i18nKey=\"comparisonAttribute\"  name=\"comparisonAttribute\"  order=\"100\"  resourceName=\"comparisonAttribute\"  syntax=\"string\"  type=\"single\"  validator=\"RequiredValueValidator0\" ></AttributeSchema><AttributeSchema i18nKey=\"comparisonOperation\"  name=\"comparisonOperation\"  order=\"200\"  resourceName=\"comparisonOperation\"  syntax=\"string\"  type=\"single_choice\"  validator=\"RequiredValueValidator0\" ><ChoiceValues><ChoiceValue i18nKey=\"comparisonOperation.PRESENT\" >PRESENT</ChoiceValue><ChoiceValue i18nKey=\"comparisonOperation.EQUALS\" >EQUALS</ChoiceValue></ChoiceValues><DefaultValues><Value>EQUALS</Value></DefaultValues></AttributeSchema><AttributeSchema i18nKey=\"comparisonValue\"  name=\"comparisonValue\"  order=\"300\"  resourceName=\"comparisonValue\"  syntax=\"string\"  type=\"single\" ><IsOptional></IsOptional></AttributeSchema><AttributeSchema i18nKey=\"identityAttribute\"  name=\"identityAttribute\"  order=\"500\"  resourceName=\"identityAttribute\"  syntax=\"string\"  type=\"single\"  validator=\"RequiredValueValidator0\" ><DefaultValues><Value>userName</Value></DefaultValues></AttributeSchema><AttributeSchema i18nKey=\"objectType\"  name=\"objectType\"  order=\"400\"  resourceName=\"objectType\"  syntax=\"string\"  type=\"single\"  validator=\"RequiredValueValidator0\" ><DefaultValues><Value>user</Value></DefaultValues></AttributeSchema><AttributeSchema name=\"RequiredValueValidator0\"  syntax=\"string\"  type=\"validator\" ><DefaultValues><Value>com.sun.identity.sm.RequiredValueValidator</Value></DefaultValues></AttributeSchema></SubSchema></Organization></Schema></Service></ServicesConfiguration>",
    "_type" : {
      "_id" : "AttributeValueDecisionNode",
      "name" : "AttributeValueDecisionNode",
      "collection" : false
    },
    "_id" : "1.0"
  }
}