{
  "metadata" : {
    "realm" : null,
    "amsterVersion" : "7.0.0-SNAPSHOT",
    "entityType" : "iPlanetAMAuthRadiusService",
    "entityId" : "1.0",
    "uid" : "ou=1.0,ou=iPlanetAMAuthRadiusService,ou=services,ou=am-config",
    "sunServiceID" : null,
    "objectClass" : [ "top", "sunService" ],
    "pathParams" : { },
    "ou" : [ ]
  },
  "data" : {
    "defaults" : {
      "primaryRadiusServers" : [ "127.0.0.1" ],
      "authenticationLevel" : 0,
      "sharedSecret" : null,
      "secondaryRadiusServers" : [ "127.0.0.1" ],
      "serverPortNumber" : 1645,
      "serverTimeout" : 3,
      "healthCheckInterval" : 5
    },
    "sunServiceSchema" : "<?xml version=\"1.0\" encoding=\"UTF-8\"?>\n\n<ServicesConfiguration><Service name=\"iPlanetAMAuthRadiusService\" version=\"1.0\"><Schema i18nFileName=\"amAuthRadius\"  i18nKey=\"iplanet-am-auth-radius-service-description\"  resourceName=\"radius\"  revisionNumber=\"30\"  serviceHierarchy=\"/DSAMEConfig/authentication/iPlanetAMAuthRadiusService\" >\n\n            <Organization hideConfigUI=\"no\" >\n                <AttributeSchema cosQualifier=\"default\"  hideConfigUI=\"no\"  i18nKey=\"a101\"  isSearchable=\"no\"  listOrder=\"natural\"  name=\"iplanet-am-auth-radius-server1\"  order=\"100\"  resourceName=\"primaryRadiusServers\"  syntax=\"string\"  type=\"list\" >\n\t\t    <DefaultValues>\n                        <Value>127.0.0.1</Value>\n\t\t    </DefaultValues>\n\t\t</AttributeSchema>\n\n                <AttributeSchema cosQualifier=\"default\"  hideConfigUI=\"no\"  i18nKey=\"a102\"  isSearchable=\"no\"  listOrder=\"natural\"  name=\"iplanet-am-auth-radius-server2\"  order=\"200\"  resourceName=\"secondaryRadiusServers\"  syntax=\"string\"  type=\"list\" >\n\t\t    <DefaultValues>\n                        <Value>127.0.0.1</Value>\n\t\t    </DefaultValues>\n\t\t</AttributeSchema>\n\n                <AttributeSchema cosQualifier=\"default\"  hideConfigUI=\"no\"  i18nKey=\"a103\"  isSearchable=\"no\"  listOrder=\"natural\"  name=\"iplanet-am-auth-radius-secret\"  order=\"300\"  resourceName=\"sharedSecret\"  syntax=\"password\"  type=\"single\" >\n\t\t</AttributeSchema>\n\t        <AttributeSchema cosQualifier=\"default\"  hideConfigUI=\"no\"  i18nKey=\"a104\"  isSearchable=\"no\"  listOrder=\"natural\"  name=\"iplanet-am-auth-radius-server-port\"  order=\"400\"  resourceName=\"serverPortNumber\"  syntax=\"number\"  type=\"single\" >\n\t\t    <DefaultValues>\n                        <Value>1645</Value>\n\t\t    </DefaultValues>\n\t\t</AttributeSchema>\n\t        <AttributeSchema cosQualifier=\"default\"  hideConfigUI=\"no\"  i18nKey=\"a500\"  isSearchable=\"no\"  listOrder=\"natural\"  name=\"iplanet-am-auth-radius-auth-level\"  order=\"700\"  rangeEnd=\"2147483647\"  rangeStart=\"0\"  resourceName=\"authenticationLevel\"  syntax=\"number_range\"  type=\"single\" >\n\t\t    <DefaultValues>\n                        <Value>0</Value>\n\t\t    </DefaultValues>\n\t\t</AttributeSchema>\n\t        <AttributeSchema cosQualifier=\"default\"  hideConfigUI=\"no\"  i18nKey=\"a105\"  isSearchable=\"no\"  listOrder=\"natural\"  name=\"iplanet-am-auth-radius-timeout\"  order=\"500\"  resourceName=\"serverTimeout\"  syntax=\"number\"  type=\"single\" >\n\t\t    <DefaultValues>\n                        <Value>3</Value>\n\t\t    </DefaultValues>\n\t\t</AttributeSchema>\n\t        <AttributeSchema cosQualifier=\"default\"  hideConfigUI=\"no\"  i18nKey=\"a106\"  isSearchable=\"no\"  listOrder=\"natural\"  name=\"openam-auth-radius-healthcheck-interval\"  order=\"600\"  resourceName=\"healthCheckInterval\"  syntax=\"number\"  type=\"single\" >\n\t\t    <DefaultValues>\n                        <Value>5</Value>\n\t\t    </DefaultValues>\n\t\t</AttributeSchema>\n\t\t<SubSchema hideConfigUI=\"no\"  inheritance=\"multiple\"  maintainPriority=\"no\"  name=\"serverconfig\"  realmCloneable=\"yes\"  resourceName=\"USE-PARENT\"  supportsApplicableOrganization=\"no\"  validate=\"yes\" >\n                    <AttributeSchema cosQualifier=\"default\"  hideConfigUI=\"no\"  i18nKey=\"a101\"  isSearchable=\"no\"  listOrder=\"natural\"  name=\"iplanet-am-auth-radius-server1\"  order=\"100\"  resourceName=\"primaryRadiusServers\"  syntax=\"string\"  type=\"list\" >\n    \t\t    <DefaultValues>\n                            <Value>127.0.0.1</Value>\n    \t\t    </DefaultValues>\n    \t\t    </AttributeSchema>\n    \n                    <AttributeSchema cosQualifier=\"default\"  hideConfigUI=\"no\"  i18nKey=\"a102\"  isSearchable=\"no\"  listOrder=\"natural\"  name=\"iplanet-am-auth-radius-server2\"  order=\"200\"  resourceName=\"secondaryRadiusServers\"  syntax=\"string\"  type=\"list\" >\n    \t\t    <DefaultValues>\n                            <Value>127.0.0.1</Value>\n    \t\t    </DefaultValues>\n    \t\t    </AttributeSchema>\n    \n                    <AttributeSchema cosQualifier=\"default\"  hideConfigUI=\"no\"  i18nKey=\"a103\"  isSearchable=\"no\"  listOrder=\"natural\"  name=\"iplanet-am-auth-radius-secret\"  order=\"300\"  resourceName=\"sharedSecret\"  syntax=\"password\"  type=\"single\" >\n    \t\t    </AttributeSchema>\n    \t            <AttributeSchema cosQualifier=\"default\"  hideConfigUI=\"no\"  i18nKey=\"a104\"  isSearchable=\"no\"  listOrder=\"natural\"  name=\"iplanet-am-auth-radius-server-port\"  order=\"400\"  resourceName=\"serverPortNumber\"  syntax=\"number\"  type=\"single\" >\n    \t\t    <DefaultValues>\n                            <Value>1645</Value>\n    \t\t    </DefaultValues>\n    \t\t    </AttributeSchema>\n    \t            <AttributeSchema cosQualifier=\"default\"  hideConfigUI=\"no\"  i18nKey=\"a500\"  isSearchable=\"no\"  listOrder=\"natural\"  name=\"iplanet-am-auth-radius-auth-level\"  order=\"700\"  rangeEnd=\"2147483647\"  rangeStart=\"0\"  resourceName=\"authenticationLevel\"  syntax=\"number_range\"  type=\"single\" >\n    \t\t    <DefaultValues>\n                            <Value>0</Value>\n    \t\t    </DefaultValues>\n    \t\t    </AttributeSchema>\n    \t            <AttributeSchema cosQualifier=\"default\"  hideConfigUI=\"no\"  i18nKey=\"a105\"  isSearchable=\"no\"  listOrder=\"natural\"  name=\"iplanet-am-auth-radius-timeout\"  order=\"500\"  resourceName=\"serverTimeout\"  syntax=\"number\"  type=\"single\" >\n    \t\t    <DefaultValues>\n                            <Value>3</Value>\n    \t\t    </DefaultValues>\n    \t\t    </AttributeSchema>\n\t            <AttributeSchema cosQualifier=\"default\"  hideConfigUI=\"no\"  i18nKey=\"a106\"  isSearchable=\"no\"  listOrder=\"natural\"  name=\"openam-auth-radius-healthcheck-interval\"  order=\"600\"  resourceName=\"healthCheckInterval\"  syntax=\"number\"  type=\"single\" >\n\t            <DefaultValues>\n                        <Value>5</Value>\n\t\t    </DefaultValues>\n                    </AttributeSchema>\n\t\t</SubSchema>\n            </Organization>\n        </Schema></Service></ServicesConfiguration>",
    "_type" : {
      "_id" : "iPlanetAMAuthRadiusService",
      "name" : "iPlanetAMAuthRadiusService",
      "collection" : false
    },
    "_id" : "1.0"
  }
}